nyctibius/__init__.py
nyctibius/__main__.py
nyctibius/bird_agent.py
nyctibius/config.py
nyctibius/harmonizer.py
nyctibius/test_queries.py
nyctibius/db/__init__.py
nyctibius/db/db_setup.py
nyctibius/db/modifier.py
nyctibius/db/querier.py
nyctibius/dto/__init__.py
nyctibius/dto/data_info.py
nyctibius/enums/__init__.py
nyctibius/enums/config_enum.py
nyctibius/enums/headers_enum.py
nyctibius/etl/__init__.py
nyctibius/etl/extractor.py
nyctibius/etl/loader.py
nyctibius/etl/transformer.py
nyctibius/utils/__init__.py
nyctibius/utils/censo_spider.py
nyctibius/utils/extractor_utils.py
nyctibius/utils/standard_spider.py
nyctibius-0.0.13.dist-info/METADATA
nyctibius-0.0.13.dist-info/WHEEL
nyctibius-0.0.13.dist-info/entry_points.txt
nyctibius-0.0.13.dist-info/top_level.txt
nyctibius-0.0.13.dist-info/RECORD
