Metadata-Version: 2.1
Name: nyctibius
Version: 0.0.13
Summary: Nyctibius is a Python package for gathering and consolidating socio-demographic data.
Home-page: https://github.com/Ersebreck/Nyctibius
Author: Erick Lozano, Diego Irreño y Cristian Amaya
Author-email: 
Project-URL: Bug Reports, https://github.com/Ersebreck/Nyctibius/issues
Project-URL: Source, https://github.com/Ersebreck/Nyctibius/
Keywords: extract transform load etl scraping relational census
Classifier: Development Status :: 2 - Pre-Alpha
Classifier: Intended Audience :: Developers
Classifier: Topic :: Software Development :: Build Tools
Classifier: License :: OSI Approved :: MIT License
Classifier: Programming Language :: Python :: 3
Classifier: Programming Language :: Python :: 3.7
Classifier: Programming Language :: Python :: 3.8
Classifier: Programming Language :: Python :: 3.9
Classifier: Programming Language :: Python :: 3.10
Classifier: Programming Language :: Python :: 3.11
Classifier: Programming Language :: Python :: 3.12
Classifier: Programming Language :: Python :: 3.13
Classifier: Programming Language :: Python :: 3 :: Only
Requires-Python: >=3.7, <4
Requires-Dist: pandas
Requires-Dist: requests
Requires-Dist: Scrapy
Requires-Dist: tqdm
Requires-Dist: pyreadstat
Requires-Dist: py7zr
Requires-Dist: pandasai
Requires-Dist: matplotlib
Requires-Dist: numpy
Provides-Extra: dev
Requires-Dist: check-manifest ; extra == 'dev'
Provides-Extra: test
Requires-Dist: coverage ; extra == 'test'
